nut_cloud/__init__.py
nut_cloud/auth.py
nut_cloud/db.py
nut_cloud/pan.py
nut_cloud/panel.py
nut_cloud/restarter.py
nut_cloud/schema.sql
nut_cloud/shop.py
nut_cloud/static/drag_and_drop.js
nut_cloud/static/favicon-192.png
nut_cloud/static/favicon-512.png
nut_cloud/static/favicon.ico
nut_cloud/static/main.js
nut_cloud/static/nutcloud.webmanifest
nut_cloud/static/style.css
nut_cloud/static/sw.js
nut_cloud/templates/base.html
nut_cloud/templates/auth/login.html
nut_cloud/templates/auth/register.html
nut_cloud/templates/auth/settings.html
nut_cloud/templates/pan/create_dir.html
nut_cloud/templates/pan/front_of_list_file.html
nut_cloud/templates/pan/index.html
nut_cloud/templates/pan/navleft.html
nut_cloud/templates/pan/safeshare.html
nut_cloud/templates/pan/share.html
nut_cloud/templates/pan/shares.html
nut_cloud/templates/panel/index.html
nut_cloud/templates/shop/addgood.html
nut_cloud/templates/shop/addpic.html
nut_cloud/templates/shop/amendgood.html
nut_cloud/templates/shop/cart.html
nut_cloud/templates/shop/categories.html
nut_cloud/templates/shop/configtickets.html
nut_cloud/templates/shop/createcategory.html
nut_cloud/templates/shop/detail.html
nut_cloud/templates/shop/index.html
nut_cloud/templates/shop/navleft.html
nut_cloud/templates/shop/tickets.html
nut_cloud/templates/shop/userinfo.html
nut_cloud-20.3.1.dist-info/LICENSE
nut_cloud-20.3.1.dist-info/METADATA
nut_cloud-20.3.1.dist-info/WHEEL
nut_cloud-20.3.1.dist-info/top_level.txt
nut_cloud-20.3.1.dist-info/RECORD
