Metadata-Version: 2.1
Name: nut-cloud
Version: 20.3.1
Summary: A website featuring a cloud drive and an online shop.
Home-page: https://github.com/NutshellySima/nut_cloud
Author: Chijun Sima, Yixue Zhong
Author-email: simachijun@gmail.com
License: MIT
Platform: UNKNOWN
Classifier: Development Status :: 3 - Alpha
Classifier: Programming Language :: Python :: 3
Classifier: Programming Language :: Python :: 3.7
Classifier: License :: OSI Approved :: MIT License
Classifier: Operating System :: OS Independent
Requires-Python: >=3
Requires-Dist: flask
Requires-Dist: zxcvbn
Requires-Dist: PyNaCl
Requires-Dist: hurry.filesize
Requires-Dist: qrcode
Requires-Dist: click
Requires-Dist: markdown2
Requires-Dist: Pillow
